scrapinghelper/__init__.py
scrapinghelper/logging.py
scrapinghelper/proxy.py
scrapinghelper/scraper.py
scrapinghelper/url.py
scrapinghelper/user_agents.py
scrapinghelper/versions.py
scrapinghelper/data/20000 User Agents.csv
scrapinghelper/data/LICENSE
scrapinghelper-0.6.5.3.dist-info/LICENSE
scrapinghelper-0.6.5.3.dist-info/METADATA
scrapinghelper-0.6.5.3.dist-info/WHEEL
scrapinghelper-0.6.5.3.dist-info/top_level.txt
scrapinghelper-0.6.5.3.dist-info/RECORD
