Metadata-Version: 2.1
Name: scrapinghelper
Version: 0.6.5.3
Summary: Utility for web scraping.
Home-page: https://github.com/iisaka51/scrapinghelper
Author: Goichi (Iisaka) Yukawa
Author-email: iisaka51@gmail.com
License: MIT
Classifier: License :: OSI Approved :: MIT License
Classifier: Programming Language :: Python :: 3.8
Classifier: Programming Language :: Python :: 3.9
Classifier: Programming Language :: Python :: 3.10
License-File: LICENSE
Requires-Dist: requests-html (>=0.10.0)
Requires-Dist: requests (>=0.10.0)
Requires-Dist: types-requests (>=2.27.29)
Requires-Dist: loguru (>=0.6.0)
Requires-Dist: numpy
Requires-Dist: pandas
Provides-Extra: converter
Requires-Dist: multimethod (>=1.8) ; extra == 'converter'
Provides-Extra: socks
Requires-Dist: PySocks (!=1.5.7,>=1.5.6) ; extra == 'socks'
